[
  {
    "id": "o13-poule-a",
    "name": "O13 Poule A",
    "halfCompetition": false,
    "temporary": false,
    "teamScores": [
      {
        "rank": 0,
        "points": 0,
        "gamesPlayed": 0,
        "gamesWon": 0,
        "gamesLost": 0,
        "gamesDraw": 0,
        "goalsFor": 0,
        "goalsAgainst": 0,
        "goalsDifference": 0,
        "teamId": "svv04-jo13-1"
      },
      {
        "rank": 1,
        "points": 0,
        "gamesPlayed": 0,
        "gamesWon": 0,
        "gamesLost": 0,
        "gamesDraw": 0,
        "goalsFor": 0,
        "goalsAgainst": 0,
        "goalsDifference": 0,
        "teamId": "dalen-dsc-jo13-1"
      },
      {
        "rank": 2,
        "points": 0,
        "gamesPlayed": 0,
        "gamesWon": 0,
        "gamesLost": 0,
        "gamesDraw": 0,
        "goalsFor": 0,
        "goalsAgainst": 0,
        "goalsDifference": 0,
        "teamId": "sv-twedo-jo13-1"
      },
      {
        "rank": 3,
        "points": 0,
        "gamesPlayed": 0,
        "gamesWon": 0,
        "gamesLost": 0,
        "gamesDraw": 0,
        "goalsFor": 0,
        "goalsAgainst": 0,
        "goalsDifference": 0,
        "teamId": "sc-erica-jo13-1"
      },
      {
        "rank": 4,
        "points": 0,
        "gamesPlayed": 0,
        "gamesWon": 0,
        "gamesLost": 0,
        "gamesDraw": 0,
        "goalsFor": 0,
        "goalsAgainst": 0,
        "goalsDifference": 0,
        "teamId": "germanicus-csvc-jo13-1"
      }
    ]
  },
  {
    "id": "o13-poule-b",
    "name": "O13 Poule B",
    "halfCompetition": false,
    "temporary": false,
    "teamScores": [
      {
        "rank": 0,
        "points": 6,
        "gamesPlayed": 2,
        "gamesWon": 2,
        "gamesLost": 0,
        "gamesDraw": 0,
        "goalsFor": 7,
        "goalsAgainst": 3,
        "goalsDifference": 4,
        "teamId": "vv-raptim-jo13-1"
      },
      {
        "rank": 1,
        "points": 6,
        "gamesPlayed": 2,
        "gamesWon": 2,
        "gamesLost": 0,
        "gamesDraw": 0,
        "goalsFor": 2,
        "goalsAgainst": 0,
        "goalsDifference": 2,
        "teamId": "vv-sleen-jo13-1"
      },
      {
        "rank": 2,
        "points": 3,
        "gamesPlayed": 2,
        "gamesWon": 1,
        "gamesLost": 1,
        "gamesDraw": 0,
        "goalsFor": 1,
        "goalsAgainst": 1,
        "goalsDifference": 0,
        "teamId": "dalen-dsc-jo13-2"
      },
      {
        "rank": 3,
        "points": 0,
        "gamesPlayed": 0,
        "gamesWon": 0,
        "gamesLost": 0,
        "gamesDraw": 0,
        "goalsFor": 0,
        "goalsAgainst": 0,
        "goalsDifference": 0,
        "teamId": "germanicus-csvc-jo13-2"
      },
      {
        "rank": 4,
        "points": 0,
        "gamesPlayed": 2,
        "gamesWon": 0,
        "gamesLost": 2,
        "gamesDraw": 0,
        "goalsFor": 2,
        "goalsAgainst": 5,
        "goalsDifference": -3,
        "teamId": "sv-twedo-jo13-2"
      },
      {
        "rank": 5,
        "points": 0,
        "gamesPlayed": 2,
        "gamesWon": 0,
        "gamesLost": 2,
        "gamesDraw": 0,
        "goalsFor": 1,
        "goalsAgainst": 4,
        "goalsDifference": -3,
        "teamId": "svv04-jo13-2"
      }
    ]
  },
  {
    "id": "o13-poule-c",
    "name": "O13 Poule C",
    "halfCompetition": false,
    "temporary": false,
    "teamScores": [
      {
        "rank": 0,
        "points": 0,
        "gamesPlayed": 0,
        "gamesWon": 0,
        "gamesLost": 0,
        "gamesDraw": 0,
        "goalsFor": 0,
        "goalsAgainst": 0,
        "goalsDifference": 0,
        "teamId": "vios-jo13-1"
      },
      {
        "rank": 1,
        "points": 0,
        "gamesPlayed": 0,
        "gamesWon": 0,
        "gamesLost": 0,
        "gamesDraw": 0,
        "goalsFor": 0,
        "goalsAgainst": 0,
        "goalsDifference": 0,
        "teamId": "vv-raptim-jo13-2"
      },
      {
        "rank": 2,
        "points": 0,
        "gamesPlayed": 0,
        "gamesWon": 0,
        "gamesLost": 0,
        "gamesDraw": 0,
        "goalsFor": 0,
        "goalsAgainst": 0,
        "goalsDifference": 0,
        "teamId": "vv-sleen-jo13-2"
      },
      {
        "rank": 3,
        "points": 0,
        "gamesPlayed": 0,
        "gamesWon": 0,
        "gamesLost": 0,
        "gamesDraw": 0,
        "goalsFor": 0,
        "goalsAgainst": 0,
        "goalsDifference": 0,
        "teamId": "dalen-dsc-jo13-3"
      },
      {
        "rank": 4,
        "points": 0,
        "gamesPlayed": 0,
        "gamesWon": 0,
        "gamesLost": 0,
        "gamesDraw": 0,
        "goalsFor": 0,
        "goalsAgainst": 0,
        "goalsDifference": 0,
        "teamId": "vv-sweel-jo13-1"
      }
    ]
  },
  {
    "id": "o13-poule-d",
    "name": "O13 Poule D",
    "halfCompetition": false,
    "temporary": false,
    "teamScores": [
      {
        "rank": 0,
        "points": 0,
        "gamesPlayed": 0,
        "gamesWon": 0,
        "gamesLost": 0,
        "gamesDraw": 0,
        "goalsFor": 0,
        "goalsAgainst": 0,
        "goalsDifference": 0,
        "teamId": "sc-erica-jo13-2"
      },
      {
        "rank": 1,
        "points": 0,
        "gamesPlayed": 0,
        "gamesWon": 0,
        "gamesLost": 0,
        "gamesDraw": 0,
        "goalsFor": 0,
        "goalsAgainst": 0,
        "goalsDifference": 0,
        "teamId": "vios-jo13-2"
      },
      {
        "rank": 2,
        "points": 0,
        "gamesPlayed": 0,
        "gamesWon": 0,
        "gamesLost": 0,
        "gamesDraw": 0,
        "goalsFor": 0,
        "goalsAgainst": 0,
        "goalsDifference": 0,
        "teamId": "vv-sweel-jo13-2"
      },
      {
        "rank": 3,
        "points": 0,
        "gamesPlayed": 0,
        "gamesWon": 0,
        "gamesLost": 0,
        "gamesDraw": 0,
        "goalsFor": 0,
        "goalsAgainst": 0,
        "goalsDifference": 0,
        "teamId": "germanicus-csvc-jo13-3"
      },
      {
        "rank": 4,
        "points": 0,
        "gamesPlayed": 0,
        "gamesWon": 0,
        "gamesLost": 0,
        "gamesDraw": 0,
        "goalsFor": 0,
        "goalsAgainst": 0,
        "goalsDifference": 0,
        "teamId": "dalen-dsc-jo13-4"
      }
    ]
  },
  {
    "id": "o13-poule-e",
    "name": "O13 Poule E",
    "halfCompetition": false,
    "temporary": false,
    "teamScores": [
      {
        "rank": 0,
        "points": 0,
        "gamesPlayed": 0,
        "gamesWon": 0,
        "gamesLost": 0,
        "gamesDraw": 0,
        "goalsFor": 0,
        "goalsAgainst": 0,
        "goalsDifference": 0,
        "teamId": "dalen-dsc-jo13-5"
      },
      {
        "rank": 1,
        "points": 0,
        "gamesPlayed": 0,
        "gamesWon": 0,
        "gamesLost": 0,
        "gamesDraw": 0,
        "goalsFor": 0,
        "goalsAgainst": 0,
        "goalsDifference": 0,
        "teamId": "vv-raptim-jo13-3"
      },
      {
        "rank": 2,
        "points": 0,
        "gamesPlayed": 0,
        "gamesWon": 0,
        "gamesLost": 0,
        "gamesDraw": 0,
        "goalsFor": 0,
        "goalsAgainst": 0,
        "goalsDifference": 0,
        "teamId": "ksc-jo13-1"
      },
      {
        "rank": 3,
        "points": 0,
        "gamesPlayed": 0,
        "gamesWon": 0,
        "gamesLost": 0,
        "gamesDraw": 0,
        "goalsFor": 0,
        "goalsAgainst": 0,
        "goalsDifference": 0,
        "teamId": "sv-twedo-jo13-3"
      },
      {
        "rank": 4,
        "points": 0,
        "gamesPlayed": 0,
        "gamesWon": 0,
        "gamesLost": 0,
        "gamesDraw": 0,
        "goalsFor": 0,
        "goalsAgainst": 0,
        "goalsDifference": 0,
        "teamId": "nkvv-protos-jo13-1"
      }
    ]
  },
  {
    "id": "o13-poule-f",
    "name": "O13 Poule F",
    "halfCompetition": false,
    "temporary": false,
    "teamScores": [
      {
        "rank": 0,
        "points": 6,
        "gamesPlayed": 2,
        "gamesWon": 2,
        "gamesLost": 0,
        "gamesDraw": 0,
        "goalsFor": 8,
        "goalsAgainst": 2,
        "goalsDifference": 6,
        "teamId": "sv-twedo-jo13-4"
      },
      {
        "rank": 1,
        "points": 6,
        "gamesPlayed": 2,
        "gamesWon": 2,
        "gamesLost": 0,
        "gamesDraw": 0,
        "goalsFor": 5,
        "goalsAgainst": 2,
        "goalsDifference": 3,
        "teamId": "nkvv-protos-jo13-2"
      },
      {
        "rank": 2,
        "points": 3,
        "gamesPlayed": 2,
        "gamesWon": 1,
        "gamesLost": 1,
        "gamesDraw": 0,
        "goalsFor": 1,
        "goalsAgainst": 5,
        "goalsDifference": -4,
        "teamId": "dalen-dsc-jo13-6"
      },
      {
        "rank": 3,
        "points": 0,
        "gamesPlayed": 0,
        "gamesWon": 0,
        "gamesLost": 0,
        "gamesDraw": 0,
        "goalsFor": 0,
        "goalsAgainst": 0,
        "goalsDifference": 0,
        "teamId": "vv-raptim-jo13-4"
      },
      {
        "rank": 4,
        "points": 0,
        "gamesPlayed": 2,
        "gamesWon": 0,
        "gamesLost": 2,
        "gamesDraw": 0,
        "goalsFor": 1,
        "goalsAgainst": 3,
        "goalsDifference": -2,
        "teamId": "germanicus-csvc-jo13-4"
      },
      {
        "rank": 5,
        "points": 0,
        "gamesPlayed": 2,
        "gamesWon": 0,
        "gamesLost": 2,
        "gamesDraw": 0,
        "goalsFor": 3,
        "goalsAgainst": 6,
        "goalsDifference": -3,
        "teamId": "ksc-jo13-2"
      }
    ]
  },
  {
    "id": "o12-poule-a",
    "name": "O12 Poule A",
    "halfCompetition": false,
    "temporary": false,
    "teamScores": [
      {
        "rank": 0,
        "points": 0,
        "gamesPlayed": 0,
        "gamesWon": 0,
        "gamesLost": 0,
        "gamesDraw": 0,
        "goalsFor": 0,
        "goalsAgainst": 0,
        "goalsDifference": 0,
        "teamId": "vios-jo12-1"
      },
      {
        "rank": 1,
        "points": 0,
        "gamesPlayed": 0,
        "gamesWon": 0,
        "gamesLost": 0,
        "gamesDraw": 0,
        "goalsFor": 0,
        "goalsAgainst": 0,
        "goalsDifference": 0,
        "teamId": "vv-sweel-mo13-1"
      },
      {
        "rank": 2,
        "points": 0,
        "gamesPlayed": 0,
        "gamesWon": 0,
        "gamesLost": 0,
        "gamesDraw": 0,
        "goalsFor": 0,
        "goalsAgainst": 0,
        "goalsDifference": 0,
        "teamId": "vv-raptim-jo12-1"
      },
      {
        "rank": 3,
        "points": 0,
        "gamesPlayed": 0,
        "gamesWon": 0,
        "gamesLost": 0,
        "gamesDraw": 0,
        "goalsFor": 0,
        "goalsAgainst": 0,
        "goalsDifference": 0,
        "teamId": "vv-raptim-jo12-2"
      },
      {
        "rank": 4,
        "points": 0,
        "gamesPlayed": 0,
        "gamesWon": 0,
        "gamesLost": 0,
        "gamesDraw": 0,
        "goalsFor": 0,
        "goalsAgainst": 0,
        "goalsDifference": 0,
        "teamId": "vv-sleen-jo12-1"
      }
    ]
  },
  {
    "id": "o12-poule-b",
    "name": "O12 Poule B",
    "halfCompetition": false,
    "temporary": false,
    "teamScores": [
      {
        "rank": 0,
        "points": 0,
        "gamesPlayed": 0,
        "gamesWon": 0,
        "gamesLost": 0,
        "gamesDraw": 0,
        "goalsFor": 0,
        "goalsAgainst": 0,
        "goalsDifference": 0,
        "teamId": "vios-jo12-2"
      },
      {
        "rank": 1,
        "points": 0,
        "gamesPlayed": 0,
        "gamesWon": 0,
        "gamesLost": 0,
        "gamesDraw": 0,
        "goalsFor": 0,
        "goalsAgainst": 0,
        "goalsDifference": 0,
        "teamId": "vv-sweel-mo13-2"
      },
      {
        "rank": 2,
        "points": 0,
        "gamesPlayed": 0,
        "gamesWon": 0,
        "gamesLost": 0,
        "gamesDraw": 0,
        "goalsFor": 0,
        "goalsAgainst": 0,
        "goalsDifference": 0,
        "teamId": "germanicus-csvc-mo12-1"
      },
      {
        "rank": 3,
        "points": 0,
        "gamesPlayed": 0,
        "gamesWon": 0,
        "gamesLost": 0,
        "gamesDraw": 0,
        "goalsFor": 0,
        "goalsAgainst": 0,
        "goalsDifference": 0,
        "teamId": "germanicus-csvc-mo12-2"
      },
      {
        "rank": 4,
        "points": 0,
        "gamesPlayed": 0,
        "gamesWon": 0,
        "gamesLost": 0,
        "gamesDraw": 0,
        "goalsFor": 0,
        "goalsAgainst": 0,
        "goalsDifference": 0,
        "teamId": "svv04-jo12-1"
      }
    ]
  },
  {
    "id": "o11-poule-a",
    "name": "O11 Poule A",
    "halfCompetition": false,
    "temporary": false,
    "teamScores": [
      {
        "rank": 0,
        "points": 0,
        "gamesPlayed": 0,
        "gamesWon": 0,
        "gamesLost": 0,
        "gamesDraw": 0,
        "goalsFor": 0,
        "goalsAgainst": 0,
        "goalsDifference": 0,
        "teamId": "vv-raptim-jo11-1"
      },
      {
        "rank": 1,
        "points": 0,
        "gamesPlayed": 0,
        "gamesWon": 0,
        "gamesLost": 0,
        "gamesDraw": 0,
        "goalsFor": 0,
        "goalsAgainst": 0,
        "goalsDifference": 0,
        "teamId": "sv-twedo-jo11-1"
      },
      {
        "rank": 2,
        "points": 0,
        "gamesPlayed": 0,
        "gamesWon": 0,
        "gamesLost": 0,
        "gamesDraw": 0,
        "goalsFor": 0,
        "goalsAgainst": 0,
        "goalsDifference": 0,
        "teamId": "svv04-jo11-1"
      },
      {
        "rank": 3,
        "points": 0,
        "gamesPlayed": 0,
        "gamesWon": 0,
        "gamesLost": 0,
        "gamesDraw": 0,
        "goalsFor": 0,
        "goalsAgainst": 0,
        "goalsDifference": 0,
        "teamId": "dalen-dsc-jo11-1"
      },
      {
        "rank": 4,
        "points": 0,
        "gamesPlayed": 0,
        "gamesWon": 0,
        "gamesLost": 0,
        "gamesDraw": 0,
        "goalsFor": 0,
        "goalsAgainst": 0,
        "goalsDifference": 0,
        "teamId": "vv-raptim-jo12-3"
      }
    ]
  },
  {
    "id": "o11-poule-b",
    "name": "O11 Poule B",
    "halfCompetition": false,
    "temporary": false,
    "teamScores": [
      {
        "rank": 0,
        "points": 0,
        "gamesPlayed": 0,
        "gamesWon": 0,
        "gamesLost": 0,
        "gamesDraw": 0,
        "goalsFor": 0,
        "goalsAgainst": 0,
        "goalsDifference": 0,
        "teamId": "sv-twedo-jo11-2"
      },
      {
        "rank": 1,
        "points": 0,
        "gamesPlayed": 0,
        "gamesWon": 0,
        "gamesLost": 0,
        "gamesDraw": 0,
        "goalsFor": 0,
        "goalsAgainst": 0,
        "goalsDifference": 0,
        "teamId": "sc-erica-jo11-1"
      },
      {
        "rank": 2,
        "points": 0,
        "gamesPlayed": 0,
        "gamesWon": 0,
        "gamesLost": 0,
        "gamesDraw": 0,
        "goalsFor": 0,
        "goalsAgainst": 0,
        "goalsDifference": 0,
        "teamId": "germanicus-csvc-jo11-1"
      },
      {
        "rank": 3,
        "points": 0,
        "gamesPlayed": 0,
        "gamesWon": 0,
        "gamesLost": 0,
        "gamesDraw": 0,
        "goalsFor": 0,
        "goalsAgainst": 0,
        "goalsDifference": 0,
        "teamId": "vv-raptim-jo11-2"
      },
      {
        "rank": 4,
        "points": 0,
        "gamesPlayed": 0,
        "gamesWon": 0,
        "gamesLost": 0,
        "gamesDraw": 0,
        "goalsFor": 0,
        "goalsAgainst": 0,
        "goalsDifference": 0,
        "teamId": "sc-erica-jo11-2"
      },
      {
        "rank": 5,
        "points": 0,
        "gamesPlayed": 0,
        "gamesWon": 0,
        "gamesLost": 0,
        "gamesDraw": 0,
        "goalsFor": 0,
        "goalsAgainst": 0,
        "goalsDifference": 0,
        "teamId": "sv-twedo-jo11-3"
      }
    ]
  },
  {
    "id": "o11-poule-c",
    "name": "O11 Poule C",
    "halfCompetition": false,
    "temporary": false,
    "teamScores": [
      {
        "rank": 0,
        "points": 0,
        "gamesPlayed": 0,
        "gamesWon": 0,
        "gamesLost": 0,
        "gamesDraw": 0,
        "goalsFor": 0,
        "goalsAgainst": 0,
        "goalsDifference": 0,
        "teamId": "dalen-dsc-jo11-2"
      },
      {
        "rank": 1,
        "points": 0,
        "gamesPlayed": 0,
        "gamesWon": 0,
        "gamesLost": 0,
        "gamesDraw": 0,
        "goalsFor": 0,
        "goalsAgainst": 0,
        "goalsDifference": 0,
        "teamId": "sv-twedo-jo11-4"
      },
      {
        "rank": 2,
        "points": 0,
        "gamesPlayed": 0,
        "gamesWon": 0,
        "gamesLost": 0,
        "gamesDraw": 0,
        "goalsFor": 0,
        "goalsAgainst": 0,
        "goalsDifference": 0,
        "teamId": "svv04-jo11-2"
      },
      {
        "rank": 3,
        "points": 0,
        "gamesPlayed": 0,
        "gamesWon": 0,
        "gamesLost": 0,
        "gamesDraw": 0,
        "goalsFor": 0,
        "goalsAgainst": 0,
        "goalsDifference": 0,
        "teamId": "nkvv-protos-jo11-1"
      },
      {
        "rank": 4,
        "points": 0,
        "gamesPlayed": 0,
        "gamesWon": 0,
        "gamesLost": 0,
        "gamesDraw": 0,
        "goalsFor": 0,
        "goalsAgainst": 0,
        "goalsDifference": 0,
        "teamId": "vv-raptim-jo11-3"
      },
      {
        "rank": 5,
        "points": 0,
        "gamesPlayed": 0,
        "gamesWon": 0,
        "gamesLost": 0,
        "gamesDraw": 0,
        "goalsFor": 0,
        "goalsAgainst": 0,
        "goalsDifference": 0,
        "teamId": "vv-sleen-jo11-1"
      }
    ]
  },
  {
    "id": "o11-poule-d",
    "name": "O11 Poule D",
    "halfCompetition": false,
    "temporary": false,
    "teamScores": [
      {
        "rank": 0,
        "points": 0,
        "gamesPlayed": 0,
        "gamesWon": 0,
        "gamesLost": 0,
        "gamesDraw": 0,
        "goalsFor": 0,
        "goalsAgainst": 0,
        "goalsDifference": 0,
        "teamId": "dalen-dsc-jo11-3"
      },
      {
        "rank": 1,
        "points": 0,
        "gamesPlayed": 0,
        "gamesWon": 0,
        "gamesLost": 0,
        "gamesDraw": 0,
        "goalsFor": 0,
        "goalsAgainst": 0,
        "goalsDifference": 0,
        "teamId": "vv-raptim-jo11-4"
      },
      {
        "rank": 2,
        "points": 0,
        "gamesPlayed": 0,
        "gamesWon": 0,
        "gamesLost": 0,
        "gamesDraw": 0,
        "goalsFor": 0,
        "goalsAgainst": 0,
        "goalsDifference": 0,
        "teamId": "ksc-jo11-1"
      },
      {
        "rank": 3,
        "points": 0,
        "gamesPlayed": 0,
        "gamesWon": 0,
        "gamesLost": 0,
        "gamesDraw": 0,
        "goalsFor": 0,
        "goalsAgainst": 0,
        "goalsDifference": 0,
        "teamId": "sc-erica-jo11-3"
      },
      {
        "rank": 4,
        "points": 0,
        "gamesPlayed": 0,
        "gamesWon": 0,
        "gamesLost": 0,
        "gamesDraw": 0,
        "goalsFor": 0,
        "goalsAgainst": 0,
        "goalsDifference": 0,
        "teamId": "vv-sweel-jo11-1"
      },
      {
        "rank": 5,
        "points": 0,
        "gamesPlayed": 0,
        "gamesWon": 0,
        "gamesLost": 0,
        "gamesDraw": 0,
        "goalsFor": 0,
        "goalsAgainst": 0,
        "goalsDifference": 0,
        "teamId": "vv-sleen-jo11-2"
      }
    ]
  },
  {
    "id": "o10-poule-a",
    "name": "O10 Poule A",
    "halfCompetition": false,
    "temporary": false,
    "teamScores": [
      {
        "rank": 0,
        "points": 0,
        "gamesPlayed": 0,
        "gamesWon": 0,
        "gamesLost": 0,
        "gamesDraw": 0,
        "goalsFor": 0,
        "goalsAgainst": 0,
        "goalsDifference": 0,
        "teamId": "dalen-dsc-jo10-1"
      },
      {
        "rank": 1,
        "points": 0,
        "gamesPlayed": 0,
        "gamesWon": 0,
        "gamesLost": 0,
        "gamesDraw": 0,
        "goalsFor": 0,
        "goalsAgainst": 0,
        "goalsDifference": 0,
        "teamId": "vv-raptim-jo10-1"
      },
      {
        "rank": 2,
        "points": 0,
        "gamesPlayed": 0,
        "gamesWon": 0,
        "gamesLost": 0,
        "gamesDraw": 0,
        "goalsFor": 0,
        "goalsAgainst": 0,
        "goalsDifference": 0,
        "teamId": "germanicus-csvc-jo10-1"
      },
      {
        "rank": 3,
        "points": 0,
        "gamesPlayed": 0,
        "gamesWon": 0,
        "gamesLost": 0,
        "gamesDraw": 0,
        "goalsFor": 0,
        "goalsAgainst": 0,
        "goalsDifference": 0,
        "teamId": "vios-jo10-1"
      },
      {
        "rank": 4,
        "points": 0,
        "gamesPlayed": 0,
        "gamesWon": 0,
        "gamesLost": 0,
        "gamesDraw": 0,
        "goalsFor": 0,
        "goalsAgainst": 0,
        "goalsDifference": 0,
        "teamId": "vv-raptim-jo9-1"
      }
    ]
  },
  {
    "id": "o10-poule-b",
    "name": "O10 Poule B",
    "halfCompetition": false,
    "temporary": false,
    "teamScores": [
      {
        "rank": 0,
        "points": 6,
        "gamesPlayed": 2,
        "gamesWon": 2,
        "gamesLost": 0,
        "gamesDraw": 0,
        "goalsFor": 9,
        "goalsAgainst": 0,
        "goalsDifference": 9,
        "teamId": "sv-twedo-jo9-1"
      },
      {
        "rank": 1,
        "points": 4,
        "gamesPlayed": 2,
        "gamesWon": 1,
        "gamesLost": 0,
        "gamesDraw": 1,
        "goalsFor": 5,
        "goalsAgainst": 3,
        "goalsDifference": 2,
        "teamId": "dalen-dsc-jo10-2"
      },
      {
        "rank": 2,
        "points": 2,
        "gamesPlayed": 2,
        "gamesWon": 0,
        "gamesLost": 0,
        "gamesDraw": 2,
        "goalsFor": 4,
        "goalsAgainst": 4,
        "goalsDifference": 0,
        "teamId": "germanicus-csvc-jo9-1"
      },
      {
        "rank": 3,
        "points": 1,
        "gamesPlayed": 2,
        "gamesWon": 0,
        "gamesLost": 1,
        "gamesDraw": 1,
        "goalsFor": 2,
        "goalsAgainst": 8,
        "goalsDifference": -6,
        "teamId": "svv04-jo10-1"
      },
      {
        "rank": 4,
        "points": 0,
        "gamesPlayed": 2,
        "gamesWon": 0,
        "gamesLost": 2,
        "gamesDraw": 0,
        "goalsFor": 1,
        "goalsAgainst": 6,
        "goalsDifference": -5,
        "teamId": "vv-raptim-jo10-2"
      }
    ]
  },
  {
    "id": "o10-poule-c",
    "name": "O10 Poule C",
    "halfCompetition": false,
    "temporary": false,
    "teamScores": [
      {
        "rank": 0,
        "points": 6,
        "gamesPlayed": 2,
        "gamesWon": 2,
        "gamesLost": 0,
        "gamesDraw": 0,
        "goalsFor": 4,
        "goalsAgainst": 2,
        "goalsDifference": 2,
        "teamId": "nkvv-protos-jo10-1"
      },
      {
        "rank": 1,
        "points": 3,
        "gamesPlayed": 2,
        "gamesWon": 1,
        "gamesLost": 1,
        "gamesDraw": 0,
        "goalsFor": 5,
        "goalsAgainst": 3,
        "goalsDifference": 2,
        "teamId": "dalen-dsc-jo10-3"
      },
      {
        "rank": 2,
        "points": 2,
        "gamesPlayed": 2,
        "gamesWon": 0,
        "gamesLost": 0,
        "gamesDraw": 2,
        "goalsFor": 2,
        "goalsAgainst": 2,
        "goalsDifference": 0,
        "teamId": "germanicus-csvc-jo10-2"
      },
      {
        "rank": 3,
        "points": 1,
        "gamesPlayed": 2,
        "gamesWon": 0,
        "gamesLost": 1,
        "gamesDraw": 1,
        "goalsFor": 1,
        "goalsAgainst": 2,
        "goalsDifference": -1,
        "teamId": "svv04-jo10-2"
      },
      {
        "rank": 4,
        "points": 1,
        "gamesPlayed": 2,
        "gamesWon": 0,
        "gamesLost": 1,
        "gamesDraw": 1,
        "goalsFor": 1,
        "goalsAgainst": 4,
        "goalsDifference": -3,
        "teamId": "ksc-jo10-1"
      }
    ]
  },
  {
    "id": "o9-poule-a",
    "name": "O9 Poule A",
    "halfCompetition": false,
    "temporary": false,
    "teamScores": [
      {
        "rank": 0,
        "points": 4,
        "gamesPlayed": 2,
        "gamesWon": 1,
        "gamesLost": 0,
        "gamesDraw": 1,
        "goalsFor": 3,
        "goalsAgainst": 0,
        "goalsDifference": 3,
        "teamId": "sv-twedo-jo9-2"
      },
      {
        "rank": 1,
        "points": 4,
        "gamesPlayed": 2,
        "gamesWon": 1,
        "gamesLost": 0,
        "gamesDraw": 1,
        "goalsFor": 2,
        "goalsAgainst": 0,
        "goalsDifference": 2,
        "teamId": "sc-erica-jo9-1"
      },
      {
        "rank": 2,
        "points": 4,
        "gamesPlayed": 2,
        "gamesWon": 1,
        "gamesLost": 0,
        "gamesDraw": 1,
        "goalsFor": 2,
        "goalsAgainst": 1,
        "goalsDifference": 1,
        "teamId": "vv-sweel-jo9-1"
      },
      {
        "rank": 3,
        "points": 1,
        "gamesPlayed": 2,
        "gamesWon": 0,
        "gamesLost": 1,
        "gamesDraw": 1,
        "goalsFor": 1,
        "goalsAgainst": 4,
        "goalsDifference": -3,
        "teamId": "vv-raptim-jo8-1"
      },
      {
        "rank": 4,
        "points": 0,
        "gamesPlayed": 0,
        "gamesWon": 0,
        "gamesLost": 0,
        "gamesDraw": 0,
        "goalsFor": 0,
        "goalsAgainst": 0,
        "goalsDifference": 0,
        "teamId": "vv-raptim-jo9-2"
      },
      {
        "rank": 5,
        "points": 0,
        "gamesPlayed": 2,
        "gamesWon": 0,
        "gamesLost": 2,
        "gamesDraw": 0,
        "goalsFor": 0,
        "goalsAgainst": 3,
        "goalsDifference": -3,
        "teamId": "dalen-dsc-jo9-1"
      }
    ]
  },
  {
    "id": "o9-poule-b",
    "name": "O9 Poule B",
    "halfCompetition": false,
    "temporary": false,
    "teamScores": [
      {
        "rank": 0,
        "points": 6,
        "gamesPlayed": 2,
        "gamesWon": 2,
        "gamesLost": 0,
        "gamesDraw": 0,
        "goalsFor": 9,
        "goalsAgainst": 3,
        "goalsDifference": 6,
        "teamId": "sc-erica-jo9-2"
      },
      {
        "rank": 1,
        "points": 6,
        "gamesPlayed": 2,
        "gamesWon": 2,
        "gamesLost": 0,
        "gamesDraw": 0,
        "goalsFor": 6,
        "goalsAgainst": 1,
        "goalsDifference": 5,
        "teamId": "svv04-jo9-1"
      },
      {
        "rank": 2,
        "points": 3,
        "gamesPlayed": 2,
        "gamesWon": 1,
        "gamesLost": 1,
        "gamesDraw": 0,
        "goalsFor": 7,
        "goalsAgainst": 4,
        "goalsDifference": 3,
        "teamId": "sc-erica-jo8-1"
      },
      {
        "rank": 3,
        "points": 0,
        "gamesPlayed": 0,
        "gamesWon": 0,
        "gamesLost": 0,
        "gamesDraw": 0,
        "goalsFor": 0,
        "goalsAgainst": 0,
        "goalsDifference": 0,
        "teamId": "vv-raptim-jo9-3"
      },
      {
        "rank": 4,
        "points": 0,
        "gamesPlayed": 2,
        "gamesWon": 0,
        "gamesLost": 2,
        "gamesDraw": 0,
        "goalsFor": 0,
        "goalsAgainst": 6,
        "goalsDifference": -6,
        "teamId": "vv-sweel-jo9-2"
      },
      {
        "rank": 5,
        "points": 0,
        "gamesPlayed": 2,
        "gamesWon": 0,
        "gamesLost": 2,
        "gamesDraw": 0,
        "goalsFor": 1,
        "goalsAgainst": 9,
        "goalsDifference": -8,
        "teamId": "sv-twedo-jo9-3"
      }
    ]
  },
  {
    "id": "o9-poule-c",
    "name": "O9 Poule C",
    "halfCompetition": false,
    "temporary": false,
    "teamScores": [
      {
        "rank": 0,
        "points": 0,
        "gamesPlayed": 0,
        "gamesWon": 0,
        "gamesLost": 0,
        "gamesDraw": 0,
        "goalsFor": 0,
        "goalsAgainst": 0,
        "goalsDifference": 0,
        "teamId": "vios-jo9-1"
      },
      {
        "rank": 1,
        "points": 0,
        "gamesPlayed": 0,
        "gamesWon": 0,
        "gamesLost": 0,
        "gamesDraw": 0,
        "goalsFor": 0,
        "goalsAgainst": 0,
        "goalsDifference": 0,
        "teamId": "vv-sweel-jo9-3"
      },
      {
        "rank": 2,
        "points": 0,
        "gamesPlayed": 0,
        "gamesWon": 0,
        "gamesLost": 0,
        "gamesDraw": 0,
        "goalsFor": 0,
        "goalsAgainst": 0,
        "goalsDifference": 0,
        "teamId": "germanicus-csvc-jo9-2"
      },
      {
        "rank": 3,
        "points": 0,
        "gamesPlayed": 0,
        "gamesWon": 0,
        "gamesLost": 0,
        "gamesDraw": 0,
        "goalsFor": 0,
        "goalsAgainst": 0,
        "goalsDifference": 0,
        "teamId": "vv-raptim-jo8-5"
      },
      {
        "rank": 4,
        "points": 0,
        "gamesPlayed": 0,
        "gamesWon": 0,
        "gamesLost": 0,
        "gamesDraw": 0,
        "goalsFor": 0,
        "goalsAgainst": 0,
        "goalsDifference": 0,
        "teamId": "vv-sleen-jo9-1"
      },
      {
        "rank": 5,
        "points": 0,
        "gamesPlayed": 0,
        "gamesWon": 0,
        "gamesLost": 0,
        "gamesDraw": 0,
        "goalsFor": 0,
        "goalsAgainst": 0,
        "goalsDifference": 0,
        "teamId": "svv04-jo9-2"
      }
    ]
  },
  {
    "id": "o8-poule-a",
    "name": "O8 Poule A",
    "halfCompetition": false,
    "temporary": false,
    "teamScores": [
      {
        "rank": 0,
        "points": 0,
        "gamesPlayed": 0,
        "gamesWon": 0,
        "gamesLost": 0,
        "gamesDraw": 0,
        "goalsFor": 0,
        "goalsAgainst": 0,
        "goalsDifference": 0,
        "teamId": "vv-raptim-jo8-2"
      },
      {
        "rank": 1,
        "points": 0,
        "gamesPlayed": 0,
        "gamesWon": 0,
        "gamesLost": 0,
        "gamesDraw": 0,
        "goalsFor": 0,
        "goalsAgainst": 0,
        "goalsDifference": 0,
        "teamId": "sv-twedo-jo8-1"
      },
      {
        "rank": 2,
        "points": 0,
        "gamesPlayed": 0,
        "gamesWon": 0,
        "gamesLost": 0,
        "gamesDraw": 0,
        "goalsFor": 0,
        "goalsAgainst": 0,
        "goalsDifference": 0,
        "teamId": "vv-raptim-jo8-3"
      },
      {
        "rank": 3,
        "points": 0,
        "gamesPlayed": 0,
        "gamesWon": 0,
        "gamesLost": 0,
        "gamesDraw": 0,
        "goalsFor": 0,
        "goalsAgainst": 0,
        "goalsDifference": 0,
        "teamId": "germanicus-csvc-jo8-1"
      },
      {
        "rank": 4,
        "points": 0,
        "gamesPlayed": 0,
        "gamesWon": 0,
        "gamesLost": 0,
        "gamesDraw": 0,
        "goalsFor": 0,
        "goalsAgainst": 0,
        "goalsDifference": 0,
        "teamId": "dalen-dsc-jo8-1"
      }
    ]
  },
  {
    "id": "o8-poule-b",
    "name": "O8 Poule B",
    "halfCompetition": false,
    "temporary": false,
    "teamScores": [
      {
        "rank": 0,
        "points": 6,
        "gamesPlayed": 2,
        "gamesWon": 2,
        "gamesLost": 0,
        "gamesDraw": 0,
        "goalsFor": 4,
        "goalsAgainst": 0,
        "goalsDifference": 4,
        "teamId": "vios-jo8-1"
      },
      {
        "rank": 1,
        "points": 6,
        "gamesPlayed": 2,
        "gamesWon": 2,
        "gamesLost": 0,
        "gamesDraw": 0,
        "goalsFor": 6,
        "goalsAgainst": 3,
        "goalsDifference": 3,
        "teamId": "vv-sweel-jo8-1"
      },
      {
        "rank": 2,
        "points": 3,
        "gamesPlayed": 2,
        "gamesWon": 1,
        "gamesLost": 1,
        "gamesDraw": 0,
        "goalsFor": 7,
        "goalsAgainst": 5,
        "goalsDifference": 2,
        "teamId": "germanicus-csvc-jo8-2"
      },
      {
        "rank": 3,
        "points": 1,
        "gamesPlayed": 2,
        "gamesWon": 0,
        "gamesLost": 1,
        "gamesDraw": 1,
        "goalsFor": 0,
        "goalsAgainst": 1,
        "goalsDifference": -1,
        "teamId": "sv-twedo-jo8-2"
      },
      {
        "rank": 4,
        "points": 1,
        "gamesPlayed": 2,
        "gamesWon": 0,
        "gamesLost": 1,
        "gamesDraw": 1,
        "goalsFor": 0,
        "goalsAgainst": 3,
        "goalsDifference": -3,
        "teamId": "svv04-jo8-1"
      },
      {
        "rank": 5,
        "points": 0,
        "gamesPlayed": 2,
        "gamesWon": 0,
        "gamesLost": 2,
        "gamesDraw": 0,
        "goalsFor": 1,
        "goalsAgainst": 6,
        "goalsDifference": -5,
        "teamId": "vv-raptim-jo8-4"
      }
    ]
  },
  {
    "id": "o8-poule-c",
    "name": "O8 Poule C",
    "halfCompetition": false,
    "temporary": false,
    "teamScores": [
      {
        "rank": 0,
        "points": 0,
        "gamesPlayed": 0,
        "gamesWon": 0,
        "gamesLost": 0,
        "gamesDraw": 0,
        "goalsFor": 0,
        "goalsAgainst": 0,
        "goalsDifference": 0,
        "teamId": "vv-raptim-jo8-6"
      },
      {
        "rank": 1,
        "points": 0,
        "gamesPlayed": 0,
        "gamesWon": 0,
        "gamesLost": 0,
        "gamesDraw": 0,
        "goalsFor": 0,
        "goalsAgainst": 0,
        "goalsDifference": 0,
        "teamId": "sv-twedo-jo8-3"
      },
      {
        "rank": 2,
        "points": 0,
        "gamesPlayed": 0,
        "gamesWon": 0,
        "gamesLost": 0,
        "gamesDraw": 0,
        "goalsFor": 0,
        "goalsAgainst": 0,
        "goalsDifference": 0,
        "teamId": "sc-erica-jo8-2"
      },
      {
        "rank": 3,
        "points": 0,
        "gamesPlayed": 0,
        "gamesWon": 0,
        "gamesLost": 0,
        "gamesDraw": 0,
        "goalsFor": 0,
        "goalsAgainst": 0,
        "goalsDifference": 0,
        "teamId": "svv04-jo8-2"
      },
      {
        "rank": 4,
        "points": 0,
        "gamesPlayed": 0,
        "gamesWon": 0,
        "gamesLost": 0,
        "gamesDraw": 0,
        "goalsFor": 0,
        "goalsAgainst": 0,
        "goalsDifference": 0,
        "teamId": "dalen-dsc-jo8-2"
      },
      {
        "rank": 5,
        "points": 0,
        "gamesPlayed": 0,
        "gamesWon": 0,
        "gamesLost": 0,
        "gamesDraw": 0,
        "goalsFor": 0,
        "goalsAgainst": 0,
        "goalsDifference": 0,
        "teamId": "germanicus-csvc-jo8-3"
      }
    ]
  },
  {
    "id": "minis",
    "name": "Mini's",
    "halfCompetition": true,
    "temporary": false,
    "teamScores": [
      {
        "rank": 0,
        "points": 0,
        "gamesPlayed": 0,
        "gamesWon": 0,
        "gamesLost": 0,
        "gamesDraw": 0,
        "goalsFor": 0,
        "goalsAgainst": 0,
        "goalsDifference": 0,
        "teamId": "svv04-m1"
      },
      {
        "rank": 1,
        "points": 0,
        "gamesPlayed": 0,
        "gamesWon": 0,
        "gamesLost": 0,
        "gamesDraw": 0,
        "goalsFor": 0,
        "goalsAgainst": 0,
        "goalsDifference": 0,
        "teamId": "vv-raptim-m1"
      },
      {
        "rank": 2,
        "points": 0,
        "gamesPlayed": 0,
        "gamesWon": 0,
        "gamesLost": 0,
        "gamesDraw": 0,
        "goalsFor": 0,
        "goalsAgainst": 0,
        "goalsDifference": 0,
        "teamId": "dalen-dsc-m1"
      },
      {
        "rank": 3,
        "points": 0,
        "gamesPlayed": 0,
        "gamesWon": 0,
        "gamesLost": 0,
        "gamesDraw": 0,
        "goalsFor": 0,
        "goalsAgainst": 0,
        "goalsDifference": 0,
        "teamId": "sc-erica-m1"
      },
      {
        "rank": 4,
        "points": 0,
        "gamesPlayed": 0,
        "gamesWon": 0,
        "gamesLost": 0,
        "gamesDraw": 0,
        "goalsFor": 0,
        "goalsAgainst": 0,
        "goalsDifference": 0,
        "teamId": "germanicus-csvc-m1"
      },
      {
        "rank": 5,
        "points": 0,
        "gamesPlayed": 0,
        "gamesWon": 0,
        "gamesLost": 0,
        "gamesDraw": 0,
        "goalsFor": 0,
        "goalsAgainst": 0,
        "goalsDifference": 0,
        "teamId": "vios-m1"
      }
    ]
  }
]