[
  {
    "id": "mini",
    "name": "Mini",
    "halfCompetition": true,
    "isFinished": false,
    "temporary": false,
    "teamScores": [
      {
        "rank": 0,
        "points": 12,
        "gamesPlayed": 4,
        "gamesWon": 4,
        "gamesLost": 0,
        "gamesDraw": 0,
        "goalsFor": 9,
        "goalsAgainst": 1,
        "goalsDifference": 8,
        "teamId": "vv-sweel-m1"
      },
      {
        "rank": 1,
        "points": 9,
        "gamesPlayed": 4,
        "gamesWon": 3,
        "gamesLost": 1,
        "gamesDraw": 0,
        "goalsFor": 10,
        "goalsAgainst": 5,
        "goalsDifference": 5,
        "teamId": "vv-raptim-m2"
      },
      {
        "rank": 2,
        "points": 8,
        "gamesPlayed": 4,
        "gamesWon": 2,
        "gamesLost": 0,
        "gamesDraw": 2,
        "goalsFor": 12,
        "goalsAgainst": 7,
        "goalsDifference": 5,
        "teamId": "vv-raptim-m1"
      },
      {
        "rank": 3,
        "points": 6,
        "gamesPlayed": 4,
        "gamesWon": 2,
        "gamesLost": 2,
        "gamesDraw": 0,
        "goalsFor": 7,
        "goalsAgainst": 6,
        "goalsDifference": 1,
        "teamId": "fc-coevorden-m1"
      },
      {
        "rank": 4,
        "points": 6,
        "gamesPlayed": 4,
        "gamesWon": 2,
        "gamesLost": 2,
        "gamesDraw": 0,
        "goalsFor": 5,
        "goalsAgainst": 7,
        "goalsDifference": -2,
        "teamId": "svv04-m2"
      },
      {
        "rank": 5,
        "points": 5,
        "gamesPlayed": 4,
        "gamesWon": 1,
        "gamesLost": 1,
        "gamesDraw": 2,
        "goalsFor": 7,
        "goalsAgainst": 5,
        "goalsDifference": 2,
        "teamId": "fc-coevorden-m2"
      },
      {
        "rank": 6,
        "points": 5,
        "gamesPlayed": 4,
        "gamesWon": 1,
        "gamesLost": 1,
        "gamesDraw": 2,
        "goalsFor": 5,
        "goalsAgainst": 6,
        "goalsDifference": -1,
        "teamId": "ksc-m1"
      },
      {
        "rank": 7,
        "points": 0,
        "gamesPlayed": 4,
        "gamesWon": 0,
        "gamesLost": 4,
        "gamesDraw": 0,
        "goalsFor": 2,
        "goalsAgainst": 11,
        "goalsDifference": -9,
        "teamId": "dalendsc-m1"
      },
      {
        "rank": 8,
        "points": 0,
        "gamesPlayed": 4,
        "gamesWon": 0,
        "gamesLost": 4,
        "gamesDraw": 0,
        "goalsFor": 1,
        "goalsAgainst": 10,
        "goalsDifference": -9,
        "teamId": "svv04-m1"
      }
    ]
  },
  {
    "id": "o8-poule-a",
    "name": "O8 Poule A",
    "halfCompetition": false,
    "isFinished": false,
    "temporary": false,
    "teamScores": [
      {
        "rank": 0,
        "points": 0,
        "gamesPlayed": 0,
        "gamesWon": 0,
        "gamesLost": 0,
        "gamesDraw": 0,
        "goalsFor": 0,
        "goalsAgainst": 0,
        "goalsDifference": 0,
        "teamId": "sc-erica-jo8-1"
      },
      {
        "rank": 1,
        "points": 0,
        "gamesPlayed": 0,
        "gamesWon": 0,
        "gamesLost": 0,
        "gamesDraw": 0,
        "goalsFor": 0,
        "goalsAgainst": 0,
        "goalsDifference": 0,
        "teamId": "vv-raptim-jo8-1"
      },
      {
        "rank": 2,
        "points": 0,
        "gamesPlayed": 0,
        "gamesWon": 0,
        "gamesLost": 0,
        "gamesDraw": 0,
        "goalsFor": 0,
        "goalsAgainst": 0,
        "goalsDifference": 0,
        "teamId": "fc-coevorden-jo8-1"
      },
      {
        "rank": 3,
        "points": 0,
        "gamesPlayed": 0,
        "gamesWon": 0,
        "gamesLost": 0,
        "gamesDraw": 0,
        "goalsFor": 0,
        "goalsAgainst": 0,
        "goalsDifference": 0,
        "teamId": "dalendsc-jo8-1"
      },
      {
        "rank": 4,
        "points": 0,
        "gamesPlayed": 0,
        "gamesWon": 0,
        "gamesLost": 0,
        "gamesDraw": 0,
        "goalsFor": 0,
        "goalsAgainst": 0,
        "goalsDifference": 0,
        "teamId": "sv-twedo-jo8-1"
      }
    ]
  },
  {
    "id": "o8-poule-b",
    "name": "O8 Poule B",
    "halfCompetition": false,
    "isFinished": false,
    "temporary": false,
    "teamScores": [
      {
        "rank": 0,
        "points": 0,
        "gamesPlayed": 0,
        "gamesWon": 0,
        "gamesLost": 0,
        "gamesDraw": 0,
        "goalsFor": 0,
        "goalsAgainst": 0,
        "goalsDifference": 0,
        "teamId": "sc-erica-jo8-2"
      },
      {
        "rank": 1,
        "points": 0,
        "gamesPlayed": 0,
        "gamesWon": 0,
        "gamesLost": 0,
        "gamesDraw": 0,
        "goalsFor": 0,
        "goalsAgainst": 0,
        "goalsDifference": 0,
        "teamId": "vv-sweel-jo8-1"
      },
      {
        "rank": 2,
        "points": 0,
        "gamesPlayed": 0,
        "gamesWon": 0,
        "gamesLost": 0,
        "gamesDraw": 0,
        "goalsFor": 0,
        "goalsAgainst": 0,
        "goalsDifference": 0,
        "teamId": "vv-raptim-jo8-2"
      },
      {
        "rank": 3,
        "points": 0,
        "gamesPlayed": 0,
        "gamesWon": 0,
        "gamesLost": 0,
        "gamesDraw": 0,
        "goalsFor": 0,
        "goalsAgainst": 0,
        "goalsDifference": 0,
        "teamId": "nkvv-protos-jo8-1"
      },
      {
        "rank": 4,
        "points": 0,
        "gamesPlayed": 0,
        "gamesWon": 0,
        "gamesLost": 0,
        "gamesDraw": 0,
        "goalsFor": 0,
        "goalsAgainst": 0,
        "goalsDifference": 0,
        "teamId": "sv-twedo-jo8-2"
      }
    ]
  },
  {
    "id": "o8-poule-c",
    "name": "O8 Poule C",
    "halfCompetition": false,
    "isFinished": false,
    "temporary": false,
    "teamScores": [
      {
        "rank": 0,
        "points": 0,
        "gamesPlayed": 0,
        "gamesWon": 0,
        "gamesLost": 0,
        "gamesDraw": 0,
        "goalsFor": 0,
        "goalsAgainst": 0,
        "goalsDifference": 0,
        "teamId": "vv-raptim-jo8-3"
      },
      {
        "rank": 1,
        "points": 0,
        "gamesPlayed": 0,
        "gamesWon": 0,
        "gamesLost": 0,
        "gamesDraw": 0,
        "goalsFor": 0,
        "goalsAgainst": 0,
        "goalsDifference": 0,
        "teamId": "fc-coevorden-jo8-2"
      },
      {
        "rank": 2,
        "points": 0,
        "gamesPlayed": 0,
        "gamesWon": 0,
        "gamesLost": 0,
        "gamesDraw": 0,
        "goalsFor": 0,
        "goalsAgainst": 0,
        "goalsDifference": 0,
        "teamId": "svv04-jo8-1"
      },
      {
        "rank": 3,
        "points": 0,
        "gamesPlayed": 0,
        "gamesWon": 0,
        "gamesLost": 0,
        "gamesDraw": 0,
        "goalsFor": 0,
        "goalsAgainst": 0,
        "goalsDifference": 0,
        "teamId": "vv-sleen-jo8-1"
      },
      {
        "rank": 4,
        "points": 0,
        "gamesPlayed": 0,
        "gamesWon": 0,
        "gamesLost": 0,
        "gamesDraw": 0,
        "goalsFor": 0,
        "goalsAgainst": 0,
        "goalsDifference": 0,
        "teamId": "vios-jo8-1"
      }
    ]
  },
  {
    "id": "o8-poule-d",
    "name": "O8 Poule D",
    "halfCompetition": false,
    "isFinished": false,
    "temporary": false,
    "teamScores": [
      {
        "rank": 0,
        "points": 0,
        "gamesPlayed": 0,
        "gamesWon": 0,
        "gamesLost": 0,
        "gamesDraw": 0,
        "goalsFor": 0,
        "goalsAgainst": 0,
        "goalsDifference": 0,
        "teamId": "vv-raptim-jo8-4"
      },
      {
        "rank": 1,
        "points": 0,
        "gamesPlayed": 0,
        "gamesWon": 0,
        "gamesLost": 0,
        "gamesDraw": 0,
        "goalsFor": 0,
        "goalsAgainst": 0,
        "goalsDifference": 0,
        "teamId": "ksc-jo8-1"
      },
      {
        "rank": 2,
        "points": 0,
        "gamesPlayed": 0,
        "gamesWon": 0,
        "gamesLost": 0,
        "gamesDraw": 0,
        "goalsFor": 0,
        "goalsAgainst": 0,
        "goalsDifference": 0,
        "teamId": "sv-twedo-jo8-3"
      },
      {
        "rank": 3,
        "points": 0,
        "gamesPlayed": 0,
        "gamesWon": 0,
        "gamesLost": 0,
        "gamesDraw": 0,
        "goalsFor": 0,
        "goalsAgainst": 0,
        "goalsDifference": 0,
        "teamId": "svv04-jo8-2"
      },
      {
        "rank": 4,
        "points": 0,
        "gamesPlayed": 0,
        "gamesWon": 0,
        "gamesLost": 0,
        "gamesDraw": 0,
        "goalsFor": 0,
        "goalsAgainst": 0,
        "goalsDifference": 0,
        "teamId": "dalendsc-jo8-2"
      },
      {
        "rank": 5,
        "points": 0,
        "gamesPlayed": 0,
        "gamesWon": 0,
        "gamesLost": 0,
        "gamesDraw": 0,
        "goalsFor": 0,
        "goalsAgainst": 0,
        "goalsDifference": 0,
        "teamId": "sv-twedo-jo8-4"
      }
    ]
  },
  {
    "id": "o9-poule-a",
    "name": "O9 Poule A",
    "halfCompetition": false,
    "isFinished": false,
    "temporary": false,
    "teamScores": [
      {
        "rank": 0,
        "points": 0,
        "gamesPlayed": 0,
        "gamesWon": 0,
        "gamesLost": 0,
        "gamesDraw": 0,
        "goalsFor": 0,
        "goalsAgainst": 0,
        "goalsDifference": 0,
        "teamId": "sc-erica-jo9-1"
      },
      {
        "rank": 1,
        "points": 0,
        "gamesPlayed": 0,
        "gamesWon": 0,
        "gamesLost": 0,
        "gamesDraw": 0,
        "goalsFor": 0,
        "goalsAgainst": 0,
        "goalsDifference": 0,
        "teamId": "vv-raptim-jo9-1"
      },
      {
        "rank": 2,
        "points": 0,
        "gamesPlayed": 0,
        "gamesWon": 0,
        "gamesLost": 0,
        "gamesDraw": 0,
        "goalsFor": 0,
        "goalsAgainst": 0,
        "goalsDifference": 0,
        "teamId": "fc-coevorden-jo9-1"
      },
      {
        "rank": 3,
        "points": 0,
        "gamesPlayed": 0,
        "gamesWon": 0,
        "gamesLost": 0,
        "gamesDraw": 0,
        "goalsFor": 0,
        "goalsAgainst": 0,
        "goalsDifference": 0,
        "teamId": "ksc-jo9-1"
      },
      {
        "rank": 4,
        "points": 0,
        "gamesPlayed": 0,
        "gamesWon": 0,
        "gamesLost": 0,
        "gamesDraw": 0,
        "goalsFor": 0,
        "goalsAgainst": 0,
        "goalsDifference": 0,
        "teamId": "svv04-jo9-1"
      },
      {
        "rank": 5,
        "points": 0,
        "gamesPlayed": 0,
        "gamesWon": 0,
        "gamesLost": 0,
        "gamesDraw": 0,
        "goalsFor": 0,
        "goalsAgainst": 0,
        "goalsDifference": 0,
        "teamId": "dalendsc-jo9-1"
      }
    ]
  },
  {
    "id": "o9-poule-b",
    "name": "O9 Poule B",
    "halfCompetition": false,
    "isFinished": false,
    "temporary": false,
    "teamScores": [
      {
        "rank": 0,
        "points": 0,
        "gamesPlayed": 0,
        "gamesWon": 0,
        "gamesLost": 0,
        "gamesDraw": 0,
        "goalsFor": 0,
        "goalsAgainst": 0,
        "goalsDifference": 0,
        "teamId": "sc-erica-jo9-2"
      },
      {
        "rank": 1,
        "points": 0,
        "gamesPlayed": 0,
        "gamesWon": 0,
        "gamesLost": 0,
        "gamesDraw": 0,
        "goalsFor": 0,
        "goalsAgainst": 0,
        "goalsDifference": 0,
        "teamId": "vv-raptim-jo9-2"
      },
      {
        "rank": 2,
        "points": 0,
        "gamesPlayed": 0,
        "gamesWon": 0,
        "gamesLost": 0,
        "gamesDraw": 0,
        "goalsFor": 0,
        "goalsAgainst": 0,
        "goalsDifference": 0,
        "teamId": "fc-coevorden-jo9-2"
      },
      {
        "rank": 3,
        "points": 0,
        "gamesPlayed": 0,
        "gamesWon": 0,
        "gamesLost": 0,
        "gamesDraw": 0,
        "goalsFor": 0,
        "goalsAgainst": 0,
        "goalsDifference": 0,
        "teamId": "vv-sleen-jo9-1"
      },
      {
        "rank": 4,
        "points": 0,
        "gamesPlayed": 0,
        "gamesWon": 0,
        "gamesLost": 0,
        "gamesDraw": 0,
        "goalsFor": 0,
        "goalsAgainst": 0,
        "goalsDifference": 0,
        "teamId": "vios-jo9-1"
      }
    ]
  },
  {
    "id": "o9-poule-c",
    "name": "O9 Poule C",
    "halfCompetition": false,
    "isFinished": false,
    "temporary": false,
    "teamScores": [
      {
        "rank": 0,
        "points": 0,
        "gamesPlayed": 0,
        "gamesWon": 0,
        "gamesLost": 0,
        "gamesDraw": 0,
        "goalsFor": 0,
        "goalsAgainst": 0,
        "goalsDifference": 0,
        "teamId": "vv-raptim-jo9-3"
      },
      {
        "rank": 1,
        "points": 0,
        "gamesPlayed": 0,
        "gamesWon": 0,
        "gamesLost": 0,
        "gamesDraw": 0,
        "goalsFor": 0,
        "goalsAgainst": 0,
        "goalsDifference": 0,
        "teamId": "fc-coevorden-jo9-3"
      },
      {
        "rank": 2,
        "points": 0,
        "gamesPlayed": 0,
        "gamesWon": 0,
        "gamesLost": 0,
        "gamesDraw": 0,
        "goalsFor": 0,
        "goalsAgainst": 0,
        "goalsDifference": 0,
        "teamId": "vv-sweel-jo9-1"
      },
      {
        "rank": 3,
        "points": 0,
        "gamesPlayed": 0,
        "gamesWon": 0,
        "gamesLost": 0,
        "gamesDraw": 0,
        "goalsFor": 0,
        "goalsAgainst": 0,
        "goalsDifference": 0,
        "teamId": "sv-twedo-jo9-1"
      },
      {
        "rank": 4,
        "points": 0,
        "gamesPlayed": 0,
        "gamesWon": 0,
        "gamesLost": 0,
        "gamesDraw": 0,
        "goalsFor": 0,
        "goalsAgainst": 0,
        "goalsDifference": 0,
        "teamId": "svv04-jo9-2"
      }
    ]
  },
  {
    "id": "o10-poule-a",
    "name": "O10 Poule A",
    "halfCompetition": false,
    "isFinished": false,
    "temporary": false,
    "teamScores": [
      {
        "rank": 0,
        "points": 0,
        "gamesPlayed": 0,
        "gamesWon": 0,
        "gamesLost": 0,
        "gamesDraw": 0,
        "goalsFor": 0,
        "goalsAgainst": 0,
        "goalsDifference": 0,
        "teamId": "sc-erica-jo10-1"
      },
      {
        "rank": 1,
        "points": 0,
        "gamesPlayed": 0,
        "gamesWon": 0,
        "gamesLost": 0,
        "gamesDraw": 0,
        "goalsFor": 0,
        "goalsAgainst": 0,
        "goalsDifference": 0,
        "teamId": "vv-raptim-jo10-1"
      },
      {
        "rank": 2,
        "points": 0,
        "gamesPlayed": 0,
        "gamesWon": 0,
        "gamesLost": 0,
        "gamesDraw": 0,
        "goalsFor": 0,
        "goalsAgainst": 0,
        "goalsDifference": 0,
        "teamId": "fc-coevorden-jo10-1"
      },
      {
        "rank": 3,
        "points": 0,
        "gamesPlayed": 0,
        "gamesWon": 0,
        "gamesLost": 0,
        "gamesDraw": 0,
        "goalsFor": 0,
        "goalsAgainst": 0,
        "goalsDifference": 0,
        "teamId": "dalendsc-jo10-1"
      },
      {
        "rank": 4,
        "points": 0,
        "gamesPlayed": 0,
        "gamesWon": 0,
        "gamesLost": 0,
        "gamesDraw": 0,
        "goalsFor": 0,
        "goalsAgainst": 0,
        "goalsDifference": 0,
        "teamId": "vv-sleen-jo10-1"
      },
      {
        "rank": 5,
        "points": 0,
        "gamesPlayed": 0,
        "gamesWon": 0,
        "gamesLost": 0,
        "gamesDraw": 0,
        "goalsFor": 0,
        "goalsAgainst": 0,
        "goalsDifference": 0,
        "teamId": "sv-twedo-jo10-1"
      }
    ]
  },
  {
    "id": "o10-poule-b",
    "name": "O10 Poule B",
    "halfCompetition": false,
    "isFinished": false,
    "temporary": false,
    "teamScores": [
      {
        "rank": 0,
        "points": 0,
        "gamesPlayed": 0,
        "gamesWon": 0,
        "gamesLost": 0,
        "gamesDraw": 0,
        "goalsFor": 0,
        "goalsAgainst": 0,
        "goalsDifference": 0,
        "teamId": "vv-sweel-jo10-1"
      },
      {
        "rank": 1,
        "points": 0,
        "gamesPlayed": 0,
        "gamesWon": 0,
        "gamesLost": 0,
        "gamesDraw": 0,
        "goalsFor": 0,
        "goalsAgainst": 0,
        "goalsDifference": 0,
        "teamId": "vv-raptim-jo10-2"
      },
      {
        "rank": 2,
        "points": 0,
        "gamesPlayed": 0,
        "gamesWon": 0,
        "gamesLost": 0,
        "gamesDraw": 0,
        "goalsFor": 0,
        "goalsAgainst": 0,
        "goalsDifference": 0,
        "teamId": "fc-coevorden-jo10-2"
      },
      {
        "rank": 3,
        "points": 0,
        "gamesPlayed": 0,
        "gamesWon": 0,
        "gamesLost": 0,
        "gamesDraw": 0,
        "goalsFor": 0,
        "goalsAgainst": 0,
        "goalsDifference": 0,
        "teamId": "svv04-jo10-1"
      },
      {
        "rank": 4,
        "points": 0,
        "gamesPlayed": 0,
        "gamesWon": 0,
        "gamesLost": 0,
        "gamesDraw": 0,
        "goalsFor": 0,
        "goalsAgainst": 0,
        "goalsDifference": 0,
        "teamId": "vios-jo10-1"
      },
      {
        "rank": 5,
        "points": 0,
        "gamesPlayed": 0,
        "gamesWon": 0,
        "gamesLost": 0,
        "gamesDraw": 0,
        "goalsFor": 0,
        "goalsAgainst": 0,
        "goalsDifference": 0,
        "teamId": "sv-twedo-jo10-2"
      }
    ]
  },
  {
    "id": "o10-poule-c",
    "name": "O10 Poule C",
    "halfCompetition": false,
    "isFinished": false,
    "temporary": false,
    "teamScores": [
      {
        "rank": 0,
        "points": 0,
        "gamesPlayed": 0,
        "gamesWon": 0,
        "gamesLost": 0,
        "gamesDraw": 0,
        "goalsFor": 0,
        "goalsAgainst": 0,
        "goalsDifference": 0,
        "teamId": "vv-sweel-jo10-2"
      },
      {
        "rank": 1,
        "points": 0,
        "gamesPlayed": 0,
        "gamesWon": 0,
        "gamesLost": 0,
        "gamesDraw": 0,
        "goalsFor": 0,
        "goalsAgainst": 0,
        "goalsDifference": 0,
        "teamId": "vv-raptim-jo10-3"
      },
      {
        "rank": 2,
        "points": 0,
        "gamesPlayed": 0,
        "gamesWon": 0,
        "gamesLost": 0,
        "gamesDraw": 0,
        "goalsFor": 0,
        "goalsAgainst": 0,
        "goalsDifference": 0,
        "teamId": "dalendsc-jo10-2"
      },
      {
        "rank": 3,
        "points": 0,
        "gamesPlayed": 0,
        "gamesWon": 0,
        "gamesLost": 0,
        "gamesDraw": 0,
        "goalsFor": 0,
        "goalsAgainst": 0,
        "goalsDifference": 0,
        "teamId": "vv-sleen-jo10-2"
      },
      {
        "rank": 4,
        "points": 0,
        "gamesPlayed": 0,
        "gamesWon": 0,
        "gamesLost": 0,
        "gamesDraw": 0,
        "goalsFor": 0,
        "goalsAgainst": 0,
        "goalsDifference": 0,
        "teamId": "sv-twedo-jo10-3"
      },
      {
        "rank": 5,
        "points": 0,
        "gamesPlayed": 0,
        "gamesWon": 0,
        "gamesLost": 0,
        "gamesDraw": 0,
        "goalsFor": 0,
        "goalsAgainst": 0,
        "goalsDifference": 0,
        "teamId": "nkvv-protos-jo10-1"
      }
    ]
  },
  {
    "id": "o11-poule-a",
    "name": "O11 Poule A",
    "halfCompetition": false,
    "isFinished": false,
    "temporary": false,
    "teamScores": [
      {
        "rank": 0,
        "points": 0,
        "gamesPlayed": 0,
        "gamesWon": 0,
        "gamesLost": 0,
        "gamesDraw": 0,
        "goalsFor": 0,
        "goalsAgainst": 0,
        "goalsDifference": 0,
        "teamId": "sc-erica-jo11-1"
      },
      {
        "rank": 1,
        "points": 0,
        "gamesPlayed": 0,
        "gamesWon": 0,
        "gamesLost": 0,
        "gamesDraw": 0,
        "goalsFor": 0,
        "goalsAgainst": 0,
        "goalsDifference": 0,
        "teamId": "vv-raptim-jo11-1"
      },
      {
        "rank": 2,
        "points": 0,
        "gamesPlayed": 0,
        "gamesWon": 0,
        "gamesLost": 0,
        "gamesDraw": 0,
        "goalsFor": 0,
        "goalsAgainst": 0,
        "goalsDifference": 0,
        "teamId": "fc-coevorden-jo11-1"
      },
      {
        "rank": 3,
        "points": 0,
        "gamesPlayed": 0,
        "gamesWon": 0,
        "gamesLost": 0,
        "gamesDraw": 0,
        "goalsFor": 0,
        "goalsAgainst": 0,
        "goalsDifference": 0,
        "teamId": "dalendsc-jo11-1"
      },
      {
        "rank": 4,
        "points": 0,
        "gamesPlayed": 0,
        "gamesWon": 0,
        "gamesLost": 0,
        "gamesDraw": 0,
        "goalsFor": 0,
        "goalsAgainst": 0,
        "goalsDifference": 0,
        "teamId": "vv-sleen-jo11-1"
      }
    ]
  },
  {
    "id": "o11-poule-b",
    "name": "O11 Poule B",
    "halfCompetition": false,
    "isFinished": false,
    "temporary": false,
    "teamScores": [
      {
        "rank": 0,
        "points": 0,
        "gamesPlayed": 0,
        "gamesWon": 0,
        "gamesLost": 0,
        "gamesDraw": 0,
        "goalsFor": 0,
        "goalsAgainst": 0,
        "goalsDifference": 0,
        "teamId": "sc-erica-jo11-2"
      },
      {
        "rank": 1,
        "points": 0,
        "gamesPlayed": 0,
        "gamesWon": 0,
        "gamesLost": 0,
        "gamesDraw": 0,
        "goalsFor": 0,
        "goalsAgainst": 0,
        "goalsDifference": 0,
        "teamId": "vv-raptim-jo11-2"
      },
      {
        "rank": 2,
        "points": 0,
        "gamesPlayed": 0,
        "gamesWon": 0,
        "gamesLost": 0,
        "gamesDraw": 0,
        "goalsFor": 0,
        "goalsAgainst": 0,
        "goalsDifference": 0,
        "teamId": "fc-coevorden-jo11-2"
      },
      {
        "rank": 3,
        "points": 0,
        "gamesPlayed": 0,
        "gamesWon": 0,
        "gamesLost": 0,
        "gamesDraw": 0,
        "goalsFor": 0,
        "goalsAgainst": 0,
        "goalsDifference": 0,
        "teamId": "vios-jo11-1"
      },
      {
        "rank": 4,
        "points": 0,
        "gamesPlayed": 0,
        "gamesWon": 0,
        "gamesLost": 0,
        "gamesDraw": 0,
        "goalsFor": 0,
        "goalsAgainst": 0,
        "goalsDifference": 0,
        "teamId": "sv-twedo-jo11-1"
      }
    ]
  },
  {
    "id": "o11-poule-c",
    "name": "O11 Poule C",
    "halfCompetition": false,
    "isFinished": false,
    "temporary": false,
    "teamScores": [
      {
        "rank": 0,
        "points": 0,
        "gamesPlayed": 0,
        "gamesWon": 0,
        "gamesLost": 0,
        "gamesDraw": 0,
        "goalsFor": 0,
        "goalsAgainst": 0,
        "goalsDifference": 0,
        "teamId": "vv-raptim-jo11-3"
      },
      {
        "rank": 1,
        "points": 0,
        "gamesPlayed": 0,
        "gamesWon": 0,
        "gamesLost": 0,
        "gamesDraw": 0,
        "goalsFor": 0,
        "goalsAgainst": 0,
        "goalsDifference": 0,
        "teamId": "fc-coevorden-jo11-3"
      },
      {
        "rank": 2,
        "points": 0,
        "gamesPlayed": 0,
        "gamesWon": 0,
        "gamesLost": 0,
        "gamesDraw": 0,
        "goalsFor": 0,
        "goalsAgainst": 0,
        "goalsDifference": 0,
        "teamId": "ksc-jo11-1"
      },
      {
        "rank": 3,
        "points": 0,
        "gamesPlayed": 0,
        "gamesWon": 0,
        "gamesLost": 0,
        "gamesDraw": 0,
        "goalsFor": 0,
        "goalsAgainst": 0,
        "goalsDifference": 0,
        "teamId": "sv-twedo-jo11-2"
      },
      {
        "rank": 4,
        "points": 0,
        "gamesPlayed": 0,
        "gamesWon": 0,
        "gamesLost": 0,
        "gamesDraw": 0,
        "goalsFor": 0,
        "goalsAgainst": 0,
        "goalsDifference": 0,
        "teamId": "svv04-jo11-1"
      },
      {
        "rank": 5,
        "points": 0,
        "gamesPlayed": 0,
        "gamesWon": 0,
        "gamesLost": 0,
        "gamesDraw": 0,
        "goalsFor": 0,
        "goalsAgainst": 0,
        "goalsDifference": 0,
        "teamId": "vv-raptim-jo11-4"
      }
    ]
  }
]